augmentedsocialscientist/__init__.py
augmentedsocialscientist/bert_abc.py
augmentedsocialscientist/bert_base.py
augmentedsocialscientist/models.py
augmentedsocialscientist-3.0.0.dist-info/LICENSE
augmentedsocialscientist-3.0.0.dist-info/METADATA
augmentedsocialscientist-3.0.0.dist-info/WHEEL
augmentedsocialscientist-3.0.0.dist-info/top_level.txt
augmentedsocialscientist-3.0.0.dist-info/RECORD
