Metadata-Version: 2.1
Name: augmentedsocialscientist
Version: 3.0.0
Summary: A Package to Easily Train Bert-Like Models for Text Classification
Home-page: https://github.com/rubingshen/augmentedsocialscientist
Download-URL: https://github.com/rubingshen/augmentedsocialscientist/archive/refs/tags/v3.0.0.tar.gz
Author: Rubing Shen
Author-email: shenrubing1996@gmail.com
License: MIT
License-File: LICENSE
Requires-Dist: scikit-learn
Requires-Dist: tqdm
Requires-Dist: numpy
Requires-Dist: scipy
Requires-Dist: torch
Requires-Dist: transformers
Requires-Dist: sentencepiece
